MANIFEST.in
README.rst
moecache.py
requirements.txt
setup.cfg
setup.py
test-requirements.txt
moecache.egg-info/PKG-INFO
moecache.egg-info/SOURCES.txt
moecache.egg-info/dependency_links.txt
moecache.egg-info/top_level.txt
moecache.egg-info/zip-safe