Metadata-Version: 1.1
Name: moecache
Version: 0.2
Summary: A memcached client with a different shading strategy
Home-page: https://github.com/lichray/moecache
Author: Zhihao Yuan
Author-email: zhihao.yuan@rackspace.com
License: ASL 2.0
Keywords: rackspace,memcached
Platform: UNKNOWN
Classifier: Development Status :: 4 - Beta
Classifier: License :: OSI Approved :: Apache Software License
Classifier: Operating System :: POSIX
Classifier: Operating System :: MacOS :: MacOS X
Classifier: Programming Language :: Python :: 2.7
Classifier: Programming Language :: Python :: 3.3
Classifier: Programming Language :: Python :: 3.4
Classifier: Programming Language :: Python :: Implementation :: PyPy
